<?xml version="1.0" encoding="UTF-8" standalone="yes"?>
<trpDocMetadata>
    <docId>561845</docId>
    <title>cod-BtQsrQ</title>
    <uploadTimestamp>1609099011994</uploadTimestamp>
    <uploader>jcwitt@loyola.edu</uploader>
    <uploaderId>25065</uploaderId>
    <nrOfPages>116</nrOfPages>
    <pageId>23073492</pageId>
    <url>https://files.transkribus.eu/Get?id=OJTEVSMADMZJHOVDUQBJOFSF&amp;fileType=view</url>
    <thumbUrl>https://files.transkribus.eu/Get?id=OJTEVSMADMZJHOVDUQBJOFSF&amp;fileType=thumb</thumbUrl>
    <externalId>NA</externalId>
    <authority>NA</authority>
    <desc>https://reader.digitale-sammlungen.de/resolve/display/bsb11111828.html

https://api.digitale-sammlungen.de/iiif/presentation/v2/bsb11111828/manifest</desc>
    <status>0</status>
    <fimgStoreColl>TrpDoc_DEA_561845</fimgStoreColl>
    <origDocId>0</origDocId>
    <collectionList>
        <colList>
            <colId>27333</colId>
            <colName>jcwitt@loyola.edu Collection</colName>
            <description>jcwitt@loyola.edu</description>
            <crowdsourcing>false</crowdsourcing>
            <elearning>false</elearning>
            <nrOfDocuments>0</nrOfDocuments>
        </colList>
    </collectionList>
</trpDocMetadata>
